cdapython/Paginator.py
cdapython/Q.py
cdapython/Qparser.py
cdapython/__init__.py
cdapython/__main__.py
cdapython/_get_unnest_clause.py
cdapython/constant_variables.py
cdapython/dataclasses/__init__.py
cdapython/dataclasses/querystr.py
cdapython/decorators/__init__.py
cdapython/decorators/cache.py
cdapython/decorators/measure.py
cdapython/endpoints.py
cdapython/error_logger.py
cdapython/exceptions/__init__.py
cdapython/exceptions/custom_exception.py
cdapython/functions.py
cdapython/progress_manager.py
cdapython/results/__init__.py
cdapython/results/count_result.py
cdapython/results/result.py
cdapython/results/string_result.py
cdapython/services/__init__.py
cdapython/services/api_count_service.py
cdapython/services/api_files_service.py
cdapython/services/api_service.py
cdapython/services/diagnosis_services.py
cdapython/services/researchsubject_services.py
cdapython/services/specimen_services.py
cdapython/services/subject_services.py
cdapython/services/treatment_services.py
cdapython/shell.py
cdapython/simple_parser.py
cdapython/utils/ConversionMap.py
cdapython/utils/__init__.py
cdapython/utils/utility.py
cdapython-2022.6.22.dist-info/LICENSE
cdapython-2022.6.22.dist-info/WHEEL
cdapython-2022.6.22.dist-info/METADATA
cdapython-2022.6.22.dist-info/RECORD
