Metadata-Version: 2.1
Name: cdapython
Version: 2022.6.22
Summary: 
License: Apache License
Author: cdadevs
Classifier: License :: Other/Proprietary License
Classifier: Programming Language :: Python :: 2
Classifier: Programming Language :: Python :: 2.7
Classifier: Programming Language :: Python :: 3
Classifier: Programming Language :: Python :: 3.10
Classifier: Programming Language :: Python :: 3.4
Classifier: Programming Language :: Python :: 3.5
Classifier: Programming Language :: Python :: 3.6
Classifier: Programming Language :: Python :: 3.7
Classifier: Programming Language :: Python :: 3.8
Classifier: Programming Language :: Python :: 3.9
Requires-Dist: ipywidgets (==7.7.0)
Requires-Dist: matplotlib (==3.5.1)
Requires-Dist: numpy (==1.21.5)
Requires-Dist: pandas (>=1.3.5,<2.0.0); python_version == "3.7" or python_version == "3.11"
Requires-Dist: python-dotenv (==0.18.0)
Requires-Dist: rich (==12.0.1)
Requires-Dist: tdparser (==1.1.6)
Requires-Dist: typing-extensions (==4.2.0)
Requires-Dist: urllib3 (==1.26.8)
Requires-Dist: wheel (==0.36.2)
